Y3S2/计算机组成原理/Lab/alu/alu.srcs/sources_1/new/alu_32bit.v
`timescale 1ns/1ps

module ALU_32bit (
    input [31:0] A,           // 输入操作数A
    input [31:0] B,           // 输入操作数B
    input [2:0] ALU_Control,  // ALU操作控制信号
    input Round_Mode,         // 舍入模式选择(0:向零舍入,1:四舍五入)
    output reg [31:0] Result, // 运算结果
    output reg SF,            // 符号标志（改为reg类型）
    output reg CF,            // 进位标志（改为reg类型）
    output reg ZF,            // 零标志（改为reg类型）
    output reg OF,            // 溢出标志（改为reg类型）
    output reg PF             // 奇偶标志（改为reg类型）
);

    // 内部信号
    wire [32:0] add_result;   // 加法结果（33位包含进位）
    wire [32:0] sub_result;   // 减法结果（33位包含借位）
    reg [31:0] rounded_result; // 舍入后结果
    
    // 运算逻辑
    always @(*) begin
        case(ALU_Control)
            3'b000: begin // 加法
                {CF, Result} = A + B;
                OF = (A[31] == B[31]) && (Result[31] != A[31]);
                SF = Result[31];
                ZF = (Result == 32'b0);
                PF = ~^Result[7:0];
            end
            3'b001: begin // 减法
                {CF, Result} = A - B;
                OF = (A[31] != B[31]) && (Result[31] != A[31]);
                SF = Result[31];
                ZF = (Result == 32'b0);
                PF = ~^Result[7:0];
            end
            3'b010: begin // 按位与
                Result = A & B;
                CF = 0; OF = 0;
                SF = Result[31];
                ZF = (Result == 32'b0);
                PF = ~^Result[7:0];
            end
            3'b011: begin // 按位或
                Result = A | B;
                CF = 0; OF = 0;
                SF = Result[31];
                ZF = (Result == 32'b0);
                PF = ~^Result[7:0];
            end
            3'b100: begin // 按位异或
                Result = A ^ B;
                CF = 0; OF = 0;
                SF = Result[31];
                ZF = (Result == 32'b0);
                PF = ~^Result[7:0];
            end
            3'b101: begin // 逻辑左移
                Result = A << B[4:0];
                CF = 0; OF = 0;
                SF = Result[31];
                ZF = (Result == 32'b0);
                PF = ~^Result[7:0];
            end
            3'b110: begin // 逻辑右移
                Result = A >> B[4:0];
                CF = 0; OF = 0;
                SF = Result[31];
                ZF = (Result == 32'b0);
                PF = ~^Result[7:0];
            end
            3'b111: begin // 算术右移
                Result = $signed(A) >>> B[4:0];
                CF = 0; OF = 0;
                SF = Result[31];
                ZF = (Result == 32'b0);
                PF = ~^Result[7:0];
            end
            default: begin
                Result = 32'b0;
                CF = 0; OF = 0;
                SF = 0;
                ZF = 1;
                PF = 1;
            end
        endcase
        
        // 舍入处理（简单示例）
        if (Round_Mode == 1'b0) begin
            rounded_result = Result; // 实际应向零舍入
        end else begin
            rounded_result = Result + (Result[0] & (|Result[31:1])); // 四舍五入
        end
    end

endmodule

Y3S2/计算机组成原理/Lab/alu/alu.srcs/sources_1/new/alu_tb.v
`timescale 1ns/1ps

module ALU_tb;

    // 输入信号
    reg [31:0] A;
    reg [31:0] B;
    reg [2:0] ALU_Control;
    reg Round_Mode;
    
    // 输出信号
    wire [31:0] Result;
    wire SF, CF, ZF, OF, PF;
    
    // 实例化被测ALU
    ALU_32bit uut (
        .A(A),
        .B(B),
        .ALU_Control(ALU_Control),
        .Round_Mode(Round_Mode),
        .Result(Result),
        .SF(SF),
        .CF(CF),
        .ZF(ZF),
        .OF(OF),
        .PF(PF)
    );
    
    // 测试过程
    initial begin
        // 初始化输入
        A = 0;
        B = 0;
        ALU_Control = 0;
        Round_Mode = 0;
        
        // 波形记录
        $dumpfile("alu_wave.vcd");
        $dumpvars(0, ALU_tb);
        
        $display("=== 开始32位ALU测试 ===");
        
        // 测试1: 算术运算
        $display("\n[测试1] 算术运算测试");
        ALU_Control = 3'b000; // 加法
        
        // 正常加法
        A = 32'd5; B = 32'd3; #10;
        $display("5 + 3 = %d (ZF=%b, CF=%b, OF=%b)", Result, ZF, CF, OF);
        
        // 溢出测试(正溢出)
        A = 32'h7FFFFFFF; B = 32'd1; #10;
        $display("MAX_INT + 1 = %h (OF=%b)", Result, OF);
        
        // 溢出测试(负溢出)
        A = 32'h80000000; B = 32'hFFFFFFFF; #10;
        $display("MIN_INT - 1 = %h (OF=%b)", Result, OF);
        
        // 测试2: 减法
        $display("\n[测试2] 减法测试");
        ALU_Control = 3'b001; // 减法
        A = 32'd10; B = 32'd4; #10;
        $display("10 - 4 = %d (CF=%b)", Result, CF);
        
        // 借位测试
        A = 32'd0; B = 32'd1; #10;
        $display("0 - 1 = %h (CF=%b)", Result, CF);
        
        // 测试3: 逻辑运算
        $display("\n[测试3] 逻辑运算测试");
        A = 32'hF0F0F0F0; B = 32'h0F0F0F0F;
        
        ALU_Control = 3'b010; #10; // 与运算
        $display("F0F0F0F0 AND 0F0F0F0F = %h", Result);
        
        ALU_Control = 3'b011; #10; // 或运算
        $display("F0F0F0F0 OR 0F0F0F0F = %h", Result);
        
        ALU_Control = 3'b100; #10; // 异或运算
        $display("F0F0F0F0 XOR 0F0F0F0F = %h", Result);
        
        // 测试4: 移位运算
        $display("\n[测试4] 移位运算测试");
        A = 32'h0000000F; B = 32'd4;
        
        ALU_Control = 3'b101; #10; // 逻辑左移
        $display("0x0000000F << 4 = %h", Result);
        
        A = 32'hF0000000;
        ALU_Control = 3'b110; #10; // 逻辑右移
        $display("0xF0000000 >> 4 = %h", Result);
        
        ALU_Control = 3'b111; #10; // 算术右移
        $display("0xF0000000 >>> 4 = %h", Result);
        
        // 测试5: 标志位专项测试
        $display("\n[测试5] 标志位测试");
        
        // 零标志测试
        ALU_Control = 3'b000; // 加法
        A = 0; B = 0; #10;
        $display("0 + 0 = %h (ZF=%b)", Result, ZF);
        
        // 符号标志测试
        A = 32'h80000000; B = 32'd1; #10;
        $display("MIN_INT + 1 = %h (SF=%b)", Result, SF);
        
        // 奇偶标志测试
        A = 32'd3; B = 32'd0; #10;
        $display("3 + 0 = %h (PF=%b)", Result, PF);
        
        // 测试完成
        $display("\n=== 所有测试完成 ===");
        #100 $finish;
    end
    
endmodule

Y3S2/计算机组成原理/Lab/alu/alu.sim/sim_1/behav/xsim/alu_wave.vcd
$date
   Thu Jun 26 18:00:46 2025
$end

$version
  2023.2
  $dumpfile ("alu_wave.vcd") 
$end

$timescale
  1ps
$end

$scope module ALU_tb $end
$var reg 32 ! A [31:0] $end
$var reg 32 " B [31:0] $end
$var reg 3 # ALU_Control [2:0] $end
$var reg 1 $ Round_Mode $end
$var wire 32 % Result [31:0] $end
$var wire 1 & SF $end
$var wire 1 ' CF $end
$var wire 1 ( ZF $end
$var wire 1 ) OF $end
$var wire 1 * PF $end
$scope module uut $end
$var wire 32 + A [31:0] $end
$var wire 32 , B [31:0] $end
$var wire 3 - ALU_Control [2:0] $end
$var wire 1 . Round_Mode $end
$var reg 32 / Result [31:0] $end
$var reg 1 0 SF $end
$var reg 1 1 CF $end
$var reg 1 2 ZF $end
$var reg 1 3 OF $end
$var reg 1 4 PF $end
$var wire 33 5 add_result [32:0] $end
$var wire 33 6 sub_result [32:0] $end
$var reg 32 7 rounded_result [31:0] $end
$upscope $end
$upscope $end
$enddefinitions $end

#0
$dumpvars
b101 !
b11 "
b0 #
0$
b1000 %
0&
0'
0(
0)
0*
b101 +
b11 ,
b0 -
0.
b1000 /
00
01
02
03
04
bz 5
bz 6
b1000 7
$end

#10000
b1111111111111111111111111111111 !
b1 "
b10000000000000000000000000000000 %
1&
1)
1*
b1111111111111111111111111111111 +
b1 ,
b10000000000000000000000000000000 /
10
13
14
b10000000000000000000000000000000 7

#20000
b10000000000000000000000000000000 !
b11111111111111111111111111111111 "
b1111111111111111111111111111111 %
0&
1'
b10000000000000000000000000000000 +
b11111111111111111111111111111111 ,
b1111111111111111111111111111111 /
00
11
b1111111111111111111111111111111 7

#30000
b1010 !
b100 "
b1 #
b110 %
0'
0)
b1010 +
b100 ,
b1 -
b110 /
01
03
b110 7

#40000
b0 !
b1 "
b11111111111111111111111111111111 %
1&
1'
b0 +
b1 ,
b11111111111111111111111111111111 /
10
11
b11111111111111111111111111111111 7

#50000
b11110000111100001111000011110000 !
b1111000011110000111100001111 "
b10 #
b0 %
0&
0'
1(
b11110000111100001111000011110000 +
b1111000011110000111100001111 ,
b10 -
b0 /
00
01
12
b0 7

#60000
b11 #
b11111111111111111111111111111111 %
1&
0(
b11 -
b11111111111111111111111111111111 /
10
02
b11111111111111111111111111111111 7

#70000
b100 #
b100 -

#80000
b1111 !
b100 "
b101 #
b11110000 %
0&
b1111 +
b100 ,
b101 -
b11110000 /
00
b11110000 7

#90000
b11110000000000000000000000000000 !
b110 #
b1111000000000000000000000000 %
b11110000000000000000000000000000 +
b110 -
b1111000000000000000000000000 /
b1111000000000000000000000000 7

#100000
b111 #
b11111111000000000000000000000000 %
1&
b111 -
b11111111000000000000000000000000 /
10
b11111111000000000000000000000000 7

#110000
b0 !
b0 "
b0 #
b0 %
0&
1(
b0 +
b0 ,
b0 -
b0 /
00
12
b0 7

#120000
b10000000000000000000000000000000 !
b1 "
b10000000000000000000000000000001 %
1&
0(
0*
b10000000000000000000000000000000 +
b1 ,
b10000000000000000000000000000001 /
10
02
04
b10000000000000000000000000000001 7

#130000
b11 !
b0 "
b11 %
0&
1*
b11 +
b0 ,
b11 /
00
14
b11 7
